acit4040_config_helper/__init__.py
acit4040_config_helper/_config_helper.py
acit4040_config_helper-0.1.3.dist-info/METADATA
acit4040_config_helper-0.1.3.dist-info/WHEEL
acit4040_config_helper-0.1.3.dist-info/RECORD
